[
  {
    "id": "2d03951a-84c9-4011-b2d6-5cbd27a6d108",
    "meeting_id": "fcea3943-f067-5b24-c9cf-d11db0ba1a55",
    "status": "synced",
    "operation": "start",
    "payload_snapshot": {
      "id": "fcea3943-f067-5b24-c9cf-d11db0ba1a55",
      "date": "2026-06-05",
      "time": "09:22:07",
      "endLat": null,
      "endLon": null,
      "status": "in_progress",
      "comment": "тестовая встреча\nПеренесено зі старої дати 04.06.2026",
      "purpose": "Презентація новинок, акційного прайсу, навчань, проектів компанії, тощо",
      "startLat": 48.44765240798194,
      "startLon": 35.05218073213646,
      "createdAt": "2026-06-05T07:24:36.765304+00:00",
      "geoManual": false,
      "updatedAt": "2026-06-05T09:22:08.047Z",
      "clientId1c": "000008574",
      "endAddress": "",
      "durationMin": null,
      "legacyOneCId": "0000001272220260604",
      "managerLogin": "itd@emet.in.ua",
      "startAddress": "Полігонна вулиця 13, Дніпро",
      "plannedAddress": "",
      "calendarEventId": null,
      "clientNameFromOneC": "Анна Шишлянникова",
      "clientPhoneFromOneC": null,
      "clientCategoryFromOneC": "Потерянный"
    },
    "onec_response": null,
    "failure_reason": "archived: pre-sync-arch",
    "retry_count": 0,
    "next_retry_at": null,
    "synced_at": "2026-06-08T11:05:14.745+00:00",
    "created_at": "2026-06-05T09:22:08.222138+00:00"
  },
  {
    "id": "33ad159c-cafd-408e-99ee-00f840716d1e",
    "meeting_id": "6e31b583-d1ae-6a50-b51d-808cc920c8ca",
    "status": "synced",
    "operation": "finish",
    "payload_snapshot": {
      "id": "6e31b583-d1ae-6a50-b51d-808cc920c8ca",
      "date": "2026-06-05",
      "time": "12:29:46",
      "endLat": 48.4476453800859,
      "endLon": 35.05222047504595,
      "status": "done",
      "comment": "тест встреч новая версия митинг\nПеренесено зі старої дати 04.06.2026",
      "purpose": "Знайомство з клієнтом, виявлення потреб, оцінка потенціалу",
      "startLat": 48.447645,
      "startLon": 35.05222,
      "createdAt": "2026-06-05T07:24:36.765304+00:00",
      "geoManual": false,
      "updatedAt": "2026-06-05T09:29:51.259Z",
      "clientId1c": "000013526",
      "endAddress": "Полігонна вулиця 13, Дніпро",
      "durationMin": null,
      "legacyOneCId": "0000001271420260604",
      "managerLogin": "itd@emet.in.ua",
      "startAddress": "Полігонна вулиця 13, Дніпро",
      "plannedAddress": "",
      "calendarEventId": null,
      "clientNameFromOneC": "Лазерхауз Интернет магазин ЛХ",
      "clientPhoneFromOneC": null,
      "clientCategoryFromOneC": "Активный"
    },
    "onec_response": null,
    "failure_reason": "archived: pre-sync-arch",
    "retry_count": 0,
    "next_retry_at": null,
    "synced_at": "2026-06-08T11:05:14.745+00:00",
    "created_at": "2026-06-05T09:29:51.428297+00:00"
  },
  {
    "id": "51d950e3-e6b4-4e78-8c55-5521300512ca",
    "meeting_id": "fcea3943-f067-5b24-c9cf-d11db0ba1a55",
    "status": "synced",
    "operation": "finish",
    "payload_snapshot": {
      "id": "fcea3943-f067-5b24-c9cf-d11db0ba1a55",
      "date": "2026-06-05",
      "time": "09:22:07",
      "endLat": 48.4476606371899,
      "endLon": 35.05215576004922,
      "status": "done",
      "comment": "тестовая встреча\nПеренесено зі старої дати 04.06.2026",
      "purpose": "Презентація новинок, акційного прайсу, навчань, проектів компанії, тощо",
      "startLat": 48.447652,
      "startLon": 35.052181,
      "createdAt": "2026-06-05T07:24:36.765304+00:00",
      "geoManual": false,
      "updatedAt": "2026-06-05T09:22:41.670Z",
      "clientId1c": "000008574",
      "endAddress": "Полігонна вулиця 13, Дніпро",
      "durationMin": null,
      "legacyOneCId": "0000001272220260604",
      "managerLogin": "itd@emet.in.ua",
      "startAddress": "Полігонна вулиця 13, Дніпро",
      "plannedAddress": "",
      "calendarEventId": null,
      "clientNameFromOneC": "Анна Шишлянникова",
      "clientPhoneFromOneC": null,
      "clientCategoryFromOneC": "Потерянный"
    },
    "onec_response": null,
    "failure_reason": "archived: pre-sync-arch",
    "retry_count": 0,
    "next_retry_at": null,
    "synced_at": "2026-06-08T11:05:14.745+00:00",
    "created_at": "2026-06-05T09:22:41.840359+00:00"
  },
  {
    "id": "6096f106-91e8-444d-b25b-a7275df407ae",
    "meeting_id": "10b86f17-0b8f-fde2-c2d8-7c7288aa6ea8",
    "status": "synced",
    "operation": "update",
    "payload_snapshot": {
      "id": "10b86f17-0b8f-fde2-c2d8-7c7288aa6ea8",
      "date": "2026-06-05",
      "time": "16:30:00",
      "endLat": null,
      "endLon": null,
      "status": "planned",
      "comment": "тестовая встреча, новый митинг\nПеренесено зі старої дати 04.06.2026",
      "purpose": "Знайомство з клієнтом, виявлення потреб, оцінка потенціалу",
      "startLat": null,
      "startLon": null,
      "createdAt": "2026-06-05T07:24:36.765304+00:00",
      "geoManual": false,
      "updatedAt": "2026-06-05T07:50:25.822Z",
      "clientId1c": "000013526",
      "endAddress": "",
      "durationMin": null,
      "legacyOneCId": "0000001271320260604",
      "managerLogin": "itd@emet.in.ua",
      "startAddress": "",
      "plannedAddress": "",
      "calendarEventId": null,
      "clientNameFromOneC": "Лазерхауз Интернет магазин ЛХ",
      "clientPhoneFromOneC": null,
      "clientCategoryFromOneC": "Активный"
    },
    "onec_response": null,
    "failure_reason": "archived: pre-sync-arch",
    "retry_count": 0,
    "next_retry_at": null,
    "synced_at": "2026-06-08T11:05:14.745+00:00",
    "created_at": "2026-06-05T07:50:26.010686+00:00"
  },
  {
    "id": "65af4062-656e-4b5c-8feb-6db9148be64a",
    "meeting_id": "a5eec281-2322-a153-3cf8-0991bfa783fb",
    "status": "synced",
    "operation": "update",
    "payload_snapshot": {
      "id": "a5eec281-2322-a153-3cf8-0991bfa783fb",
      "date": "2026-06-04",
      "time": "16:30:00",
      "endLat": null,
      "endLon": null,
      "status": "cancelled",
      "comment": "тестовая встреча, новый митинг",
      "purpose": "Знайомство з клієнтом, виявлення потреб, оцінка потенціалу",
      "startLat": null,
      "startLon": null,
      "createdAt": "2026-06-05T07:24:36.765304+00:00",
      "geoManual": false,
      "updatedAt": "2026-06-05T07:49:25.971Z",
      "clientId1c": "000013526",
      "endAddress": "",
      "durationMin": null,
      "legacyOneCId": "0000001272020260604",
      "managerLogin": "itd@emet.in.ua",
      "startAddress": "",
      "plannedAddress": "",
      "calendarEventId": null,
      "clientNameFromOneC": "Лазерхауз Интернет магазин ЛХ",
      "clientPhoneFromOneC": null,
      "clientCategoryFromOneC": "Активный"
    },
    "onec_response": null,
    "failure_reason": "archived: pre-sync-arch",
    "retry_count": 0,
    "next_retry_at": null,
    "synced_at": "2026-06-08T11:05:14.745+00:00",
    "created_at": "2026-06-05T07:49:26.155375+00:00"
  },
  {
    "id": "7421ea57-71aa-4e59-a60a-b45fd9a2e713",
    "meeting_id": "10b86f17-0b8f-fde2-c2d8-7c7288aa6ea8",
    "status": "synced",
    "operation": "start",
    "payload_snapshot": {
      "id": "10b86f17-0b8f-fde2-c2d8-7c7288aa6ea8",
      "date": "2026-06-05",
      "time": "16:30:00",
      "endLat": null,
      "endLon": null,
      "status": "in_progress",
      "comment": "тестовая встреча, новый митинг\nПеренесено зі старої дати 04.06.2026",
      "purpose": "Знайомство з клієнтом, виявлення потреб, оцінка потенціалу",
      "startLat": 48.447628988917224,
      "startLon": 35.05221790759961,
      "createdAt": "2026-06-05T07:24:36.765304+00:00",
      "geoManual": false,
      "updatedAt": "2026-06-05T07:50:34.437Z",
      "clientId1c": "000013526",
      "endAddress": "",
      "durationMin": null,
      "legacyOneCId": "0000001271320260604",
      "managerLogin": "itd@emet.in.ua",
      "startAddress": "Полігонна вулиця 13, Дніпро",
      "plannedAddress": "",
      "calendarEventId": null,
      "clientNameFromOneC": "Лазерхауз Интернет магазин ЛХ",
      "clientPhoneFromOneC": null,
      "clientCategoryFromOneC": "Активный"
    },
    "onec_response": null,
    "failure_reason": "archived: pre-sync-arch",
    "retry_count": 0,
    "next_retry_at": null,
    "synced_at": "2026-06-08T11:05:14.745+00:00",
    "created_at": "2026-06-05T07:50:34.939839+00:00"
  },
  {
    "id": "771e8d91-f89c-40f3-9cdb-642cd964ec2a",
    "meeting_id": "6e31b583-d1ae-6a50-b51d-808cc920c8ca",
    "status": "synced",
    "operation": "start",
    "payload_snapshot": {
      "id": "6e31b583-d1ae-6a50-b51d-808cc920c8ca",
      "date": "2026-06-05",
      "time": "12:29:46",
      "endLat": null,
      "endLon": null,
      "status": "in_progress",
      "comment": "тест встреч новая версия митинг\nПеренесено зі старої дати 04.06.2026",
      "purpose": "Знайомство з клієнтом, виявлення потреб, оцінка потенціалу",
      "startLat": 48.4476453800859,
      "startLon": 35.05222047504595,
      "createdAt": "2026-06-05T07:24:36.765304+00:00",
      "geoManual": false,
      "updatedAt": "2026-06-05T09:29:46.659Z",
      "clientId1c": "000013526",
      "endAddress": "",
      "durationMin": null,
      "legacyOneCId": "0000001271420260604",
      "managerLogin": "itd@emet.in.ua",
      "startAddress": "Полігонна вулиця 13, Дніпро",
      "plannedAddress": "",
      "calendarEventId": null,
      "clientNameFromOneC": "Лазерхауз Интернет магазин ЛХ",
      "clientPhoneFromOneC": null,
      "clientCategoryFromOneC": "Активный"
    },
    "onec_response": null,
    "failure_reason": "archived: pre-sync-arch",
    "retry_count": 0,
    "next_retry_at": null,
    "synced_at": "2026-06-08T11:05:14.745+00:00",
    "created_at": "2026-06-05T09:29:46.838922+00:00"
  },
  {
    "id": "7dd6dc6f-9c03-4593-ade1-02cd70e0156c",
    "meeting_id": "fcea3943-f067-5b24-c9cf-d11db0ba1a55",
    "status": "synced",
    "operation": "update",
    "payload_snapshot": {
      "id": "fcea3943-f067-5b24-c9cf-d11db0ba1a55",
      "date": "2026-06-05",
      "time": "17:30:00",
      "endLat": null,
      "endLon": null,
      "status": "planned",
      "comment": "тестовая встреча\nПеренесено зі старої дати 04.06.2026",
      "purpose": "Презентація новинок, акційного прайсу, навчань, проектів компанії, тощо",
      "startLat": null,
      "startLon": null,
      "createdAt": "2026-06-05T07:24:36.765304+00:00",
      "geoManual": false,
      "updatedAt": "2026-06-05T09:21:51.565Z",
      "clientId1c": "000008574",
      "endAddress": "",
      "durationMin": null,
      "legacyOneCId": "0000001272220260604",
      "managerLogin": "itd@emet.in.ua",
      "startAddress": "",
      "plannedAddress": "",
      "calendarEventId": null,
      "clientNameFromOneC": "Анна Шишлянникова",
      "clientPhoneFromOneC": null,
      "clientCategoryFromOneC": "Потерянный"
    },
    "onec_response": null,
    "failure_reason": "archived: pre-sync-arch",
    "retry_count": 0,
    "next_retry_at": null,
    "synced_at": "2026-06-08T11:05:14.745+00:00",
    "created_at": "2026-06-05T09:21:51.928571+00:00"
  },
  {
    "id": "9530b5cc-d2e0-4d39-a587-9ba710302a0e",
    "meeting_id": "d9845e9b-9436-4d94-9be8-3f27bdc476fc",
    "status": "synced",
    "operation": "save",
    "payload_snapshot": {
      "id": "d9845e9b-9436-4d94-9be8-3f27bdc476fc",
      "date": "2026-06-08",
      "time": "12:00:00",
      "endLat": null,
      "endLon": null,
      "status": "planned",
      "comment": "Тестовая встреча, новое приложение",
      "purpose": "Знайомство з клієнтом, виявлення потреб, оцінка потенціалу",
      "startLat": null,
      "startLon": null,
      "createdAt": "2026-06-08T08:32:34.259056+00:00",
      "geoManual": false,
      "startedAt": null,
      "updatedAt": "2026-06-08T08:32:34.259056+00:00",
      "clientId1c": "000003483",
      "clientName": null,
      "endAddress": null,
      "finishedAt": null,
      "clientPhone": null,
      "durationMin": 45,
      "legacyOneCId": null,
      "managerLogin": "itd@emet.in.ua",
      "startAddress": null,
      "anketaDataJson": null,
      "plannedAddress": null,
      "calendarEventId": null,
      "clientNameFromOneC": null,
      "clientPhoneFromOneC": null,
      "clientCategoryFromOneC": null
    },
    "onec_response": null,
    "failure_reason": "archived: pre-sync-arch",
    "retry_count": 0,
    "next_retry_at": null,
    "synced_at": "2026-06-08T11:05:14.745+00:00",
    "created_at": "2026-06-08T08:32:34.412834+00:00"
  },
  {
    "id": "a6031d89-2b99-421a-9a1c-2b266dca7750",
    "meeting_id": "6e31b583-d1ae-6a50-b51d-808cc920c8ca",
    "status": "synced",
    "operation": "update",
    "payload_snapshot": {
      "id": "6e31b583-d1ae-6a50-b51d-808cc920c8ca",
      "date": "2026-06-06",
      "time": "17:00:00",
      "endLat": null,
      "endLon": null,
      "status": "planned",
      "comment": "тест встреч новая версия митинг\nПеренесено зі старої дати 04.06.2026",
      "purpose": "Знайомство з клієнтом, виявлення потреб, оцінка потенціалу",
      "startLat": null,
      "startLon": null,
      "createdAt": "2026-06-05T07:24:36.765304+00:00",
      "geoManual": false,
      "updatedAt": "2026-06-05T09:29:17.987Z",
      "clientId1c": "000013526",
      "endAddress": "",
      "durationMin": null,
      "legacyOneCId": "0000001271420260604",
      "managerLogin": "itd@emet.in.ua",
      "startAddress": "",
      "plannedAddress": "",
      "calendarEventId": null,
      "clientNameFromOneC": "Лазерхауз Интернет магазин ЛХ",
      "clientPhoneFromOneC": null,
      "clientCategoryFromOneC": "Активный"
    },
    "onec_response": null,
    "failure_reason": "archived: pre-sync-arch",
    "retry_count": 0,
    "next_retry_at": null,
    "synced_at": "2026-06-08T11:05:14.745+00:00",
    "created_at": "2026-06-05T09:29:18.149806+00:00"
  },
  {
    "id": "b4492a1f-e444-45f5-8226-2e729e3ab274",
    "meeting_id": "d9845e9b-9436-4d94-9be8-3f27bdc476fc",
    "status": "synced",
    "operation": "start",
    "payload_snapshot": {
      "id": "d9845e9b-9436-4d94-9be8-3f27bdc476fc",
      "date": "2026-06-08",
      "time": "11:33:50",
      "endLat": null,
      "endLon": null,
      "status": "in_progress",
      "comment": "Тестовая встреча, новое приложение",
      "purpose": "Знайомство з клієнтом, виявлення потреб, оцінка потенціалу",
      "startLat": 48.447644,
      "startLon": 35.052119,
      "createdAt": "2026-06-08T08:32:34.259056+00:00",
      "geoManual": false,
      "startedAt": "2026-06-08T08:33:50.452+00:00",
      "updatedAt": "2026-06-08T08:33:50.575586+00:00",
      "clientId1c": "000003483",
      "clientName": "Коломийчук Елена Владимировна,ЧК",
      "endAddress": null,
      "finishedAt": null,
      "clientPhone": null,
      "durationMin": 45,
      "legacyOneCId": "0000001287920260608",
      "managerLogin": "itd@emet.in.ua",
      "startAddress": "Полігонна вулиця 13, Дніпро",
      "anketaDataJson": "",
      "plannedAddress": null,
      "calendarEventId": null,
      "clientNameFromOneC": "Коломийчук Елена Владимировна,ЧК",
      "clientPhoneFromOneC": null,
      "clientCategoryFromOneC": "Спящий"
    },
    "onec_response": null,
    "failure_reason": "archived: pre-sync-arch",
    "retry_count": 0,
    "next_retry_at": null,
    "synced_at": "2026-06-08T11:05:14.745+00:00",
    "created_at": "2026-06-08T08:33:50.718747+00:00"
  },
  {
    "id": "f61f261f-babe-4b20-8623-e18ebbec6b96",
    "meeting_id": "10b86f17-0b8f-fde2-c2d8-7c7288aa6ea8",
    "status": "synced",
    "operation": "finish",
    "payload_snapshot": {
      "id": "10b86f17-0b8f-fde2-c2d8-7c7288aa6ea8",
      "date": "2026-06-05",
      "time": "16:30:00",
      "endLat": 48.447628988917224,
      "endLon": 35.05221790759961,
      "status": "done",
      "comment": "тестовая встреча, новый митинг\nПеренесено зі старої дати 04.06.2026",
      "purpose": "Знайомство з клієнтом, виявлення потреб, оцінка потенціалу",
      "startLat": 48.447629,
      "startLon": 35.052218,
      "createdAt": "2026-06-05T07:24:36.765304+00:00",
      "geoManual": false,
      "updatedAt": "2026-06-05T07:50:56.061Z",
      "clientId1c": "000013526",
      "endAddress": "Полігонна вулиця 13, Дніпро",
      "durationMin": null,
      "legacyOneCId": "0000001271320260604",
      "managerLogin": "itd@emet.in.ua",
      "startAddress": "Полігонна вулиця 13, Дніпро",
      "plannedAddress": "",
      "calendarEventId": null,
      "clientNameFromOneC": "Лазерхауз Интернет магазин ЛХ",
      "clientPhoneFromOneC": null,
      "clientCategoryFromOneC": "Активный"
    },
    "onec_response": null,
    "failure_reason": "archived: pre-sync-arch",
    "retry_count": 0,
    "next_retry_at": null,
    "synced_at": "2026-06-08T11:05:14.745+00:00",
    "created_at": "2026-06-05T07:50:56.542672+00:00"
  }
]